{
  "source": {
    "name": "NYS Tax Dept Publication 718",
    "url": "https://www.tax.ny.gov/pdf/publications/sales/pub718.pdf"
  },
  "consts": {
    "state_rate": 0.04,
    "mctd_rate": 0.00375
  },
  "mctd_counties": [
    "Bronx",
    "Kings",
    "New York",
    "Queens",
    "Richmond",
    "Dutchess",
    "Nassau",
    "Orange",
    "Putnam",
    "Rockland",
    "Suffolk",
    "Westchester"
  ],
  "counties": {
    "Albany": { "county_rate": 0.04, "composite_rate": 0.08, "reporting_code": "0181" },
    "Allegany": { "county_rate": 0.045, "composite_rate": 0.085, "reporting_code": "0221" },
    "Broome": { "county_rate": 0.04, "composite_rate": 0.08, "reporting_code": "0321" },
    "Cattaraugus": { "county_rate": 0.04, "composite_rate": 0.08, "reporting_code": "0481" },
    "Cayuga": { "county_rate": 0.04, "composite_rate": 0.08, "reporting_code": "0511" },
    "Chautauqua": { "county_rate": 0.04, "composite_rate": 0.08, "reporting_code": "0651" },
    "Chemung": { "county_rate": 0.04, "composite_rate": 0.08, "reporting_code": "0711" },
    "Chenango": { "county_rate": 0.04, "composite_rate": 0.08, "reporting_code": "0861" },
    "Clinton": { "county_rate": 0.04, "composite_rate": 0.08, "reporting_code": "0921" },
    "Columbia": { "county_rate": 0.04, "composite_rate": 0.08, "reporting_code": "1021" },
    "Cortland": { "county_rate": 0.04, "composite_rate": 0.08, "reporting_code": "1131" },
    "Delaware": { "county_rate": 0.04, "composite_rate": 0.08, "reporting_code": "1221" },
    "Dutchess": { "county_rate": 0.0375, "composite_rate": 0.08125, "reporting_code": "1311" },
    "Erie": { "county_rate": 0.0475, "composite_rate": 0.0875, "reporting_code": "1451" },
    "Essex": { "county_rate": 0.04, "composite_rate": 0.08, "reporting_code": "1521" },
    "Franklin": { "county_rate": 0.04, "composite_rate": 0.08, "reporting_code": "1621" },
    "Fulton": { "county_rate": 0.04, "composite_rate": 0.08, "reporting_code": "1791" },
    "Genesee": { "county_rate": 0.04, "composite_rate": 0.08, "reporting_code": "1811" },
    "Greene": { "county_rate": 0.04, "composite_rate": 0.08, "reporting_code": "1911" },
    "Hamilton": { "county_rate": 0.04, "composite_rate": 0.08, "reporting_code": "2011" },
    "Herkimer": { "county_rate": 0.0425, "composite_rate": 0.0825, "reporting_code": "2121" },
    "Jefferson": { "county_rate": 0.04, "composite_rate": 0.08, "reporting_code": "2221" },
    "Lewis": { "county_rate": 0.04, "composite_rate": 0.08, "reporting_code": "2321" },
    "Livingston": { "county_rate": 0.04, "composite_rate": 0.08, "reporting_code": "2411" },
    "Madison": { "county_rate": 0.04, "composite_rate": 0.08, "reporting_code": "2511" },
    "Monroe": { "county_rate": 0.04, "composite_rate": 0.08, "reporting_code": "2611" },
    "Montgomery": { "county_rate": 0.04, "composite_rate": 0.08, "reporting_code": "2781" },
    "Nassau": { "county_rate": 0.0425, "composite_rate": 0.08625, "reporting_code": "2811" },
    "Niagara": { "county_rate": 0.04, "composite_rate": 0.08, "reporting_code": "2911" },
    "Oneida": { "county_rate": 0.0475, "composite_rate": 0.0875, "reporting_code": "3010" },
    "Onondaga": { "county_rate": 0.04, "composite_rate": 0.08, "reporting_code": "3121" },
    "Ontario": { "county_rate": 0.035, "composite_rate": 0.075, "reporting_code": "3211" },
    "Orange": { "county_rate": 0.0375, "composite_rate": 0.08125, "reporting_code": "3321" },
    "Orleans": { "county_rate": 0.04, "composite_rate": 0.08, "reporting_code": "3481" },
    "Oswego": { "county_rate": 0.04, "composite_rate": 0.08, "reporting_code": "3501" },
    "Otsego": { "county_rate": 0.04, "composite_rate": 0.08, "reporting_code": "3621" },
    "Putnam": { "county_rate": 0.04, "composite_rate": 0.08375, "reporting_code": "3731" },
    "Rensselaer": { "county_rate": 0.04, "composite_rate": 0.08, "reporting_code": "3881" },
    "Rockland": { "county_rate": 0.04, "composite_rate": 0.08375, "reporting_code": "3921" },
    "St. Lawrence": { "county_rate": 0.04, "composite_rate": 0.08, "reporting_code": "4091" },
    "Saratoga": { "county_rate": 0.03, "composite_rate": 0.07, "reporting_code": "4111" },
    "Schenectady": { "county_rate": 0.04, "composite_rate": 0.08, "reporting_code": "4241" },
    "Schoharie": { "county_rate": 0.04, "composite_rate": 0.08, "reporting_code": "4321" },
    "Schuyler": { "county_rate": 0.04, "composite_rate": 0.08, "reporting_code": "4411" },
    "Seneca": { "county_rate": 0.04, "composite_rate": 0.08, "reporting_code": "4511" },
    "Steuben": { "county_rate": 0.04, "composite_rate": 0.08, "reporting_code": "4691" },
    "Suffolk": { "county_rate": 0.0425, "composite_rate": 0.08625, "reporting_code": "4711" },
    "Sullivan": { "county_rate": 0.04, "composite_rate": 0.08, "reporting_code": "4821" },
    "Tioga": { "county_rate": 0.04, "composite_rate": 0.08, "reporting_code": "4921" },
    "Tompkins": { "county_rate": 0.04, "composite_rate": 0.08, "reporting_code": "5081" },
    "Ulster": { "county_rate": 0.04, "composite_rate": 0.08, "reporting_code": "5111" },
    "Warren": { "county_rate": 0.03, "composite_rate": 0.07, "reporting_code": "5281" },
    "Washington": { "county_rate": 0.03, "composite_rate": 0.07, "reporting_code": "5311" },
    "Wayne": { "county_rate": 0.04, "composite_rate": 0.08, "reporting_code": "5421" },
    "Westchester": { "county_rate": 0.04, "composite_rate": 0.08375, "reporting_code": "5581" },
    "Wyoming": { "county_rate": 0.04, "composite_rate": 0.08, "reporting_code": "5621" },
    "Yates": { "county_rate": 0.04, "composite_rate": 0.08, "reporting_code": "5721" },
    "New York City": { "county_rate": 0.045, "composite_rate": 0.08875, "reporting_code": "8081" }
  },
  "cities_exceptions": {
    "Mount Vernon": { "city_rate": 0.045, "composite_rate": 0.08875, "reporting_code": "5521", "parent_county": "Westchester" },
    "Yonkers": { "city_rate": 0.045, "composite_rate": 0.08875, "reporting_code": "6511", "parent_county": "Westchester" }
  }
}